{"version":1,"resource":"vscode-remote://wsl%2Bubuntu/home/mattmcgovern/code/mmcgovern25/fullstack-challenges/04-Front-End/01-HTML-and-CSS/02-Fonts-and-colors/profile/style.css","entries":[{"id":"Jseb.css","timestamp":1691426096321},{"id":"qBhy.css","timestamp":1691426265375},{"id":"BL9d.css","timestamp":1691426532806},{"id":"9x1e.css","timestamp":1691426576226},{"id":"UN7z.css","timestamp":1691426617187},{"id":"M5yF.css","timestamp":1691426651778},{"id":"DGgR.css","timestamp":1691426692295},{"id":"VpEf.css","timestamp":1691426774487},{"id":"kqqt.css","timestamp":1691426809739},{"id":"oyj4.css","timestamp":1691426944116},{"id":"I63r.css","timestamp":1691427466390},{"id":"SLzl.css","timestamp":1691427510775},{"id":"oEPr.css","timestamp":1691427555462},{"id":"3yHA.css","timestamp":1691427579490},{"id":"2KHl.css","timestamp":1691427607007},{"id":"1vZt.css","timestamp":1691427620083},{"id":"3ExK.css","timestamp":1691427822850},{"id":"WsgX.css","timestamp":1691427895683},{"id":"rO5l.css","timestamp":1691428027817},{"id":"ftFA.css","timestamp":1691428039495},{"id":"XmwN.css","timestamp":1691428626088},{"id":"RWdO.css","timestamp":1691428642576},{"id":"E2hH.css","timestamp":1691428672682},{"id":"20lQ.css","timestamp":1691428749176},{"id":"ouhO.css","timestamp":1691428777668},{"id":"bolx.css","timestamp":1691428832647},{"id":"qWSo.css","timestamp":1691428858961},{"id":"zXKY.css","timestamp":1691428875352},{"id":"oOXj.css","timestamp":1691428892945},{"id":"jQeQ.css","timestamp":1691428905978},{"id":"MjQm.css","timestamp":1691429004333},{"id":"RDOW.css","timestamp":1691429059096},{"id":"uz7N.css","timestamp":1691429134453},{"id":"Q71x.css","timestamp":1691429147409},{"id":"5PA6.css","timestamp":1691430899267},{"id":"FbTp.css","timestamp":1691430984363},{"id":"Rxko.css","timestamp":1691431114114},{"id":"tXWV.css","timestamp":1691431140071},{"id":"5WeY.css","timestamp":1691431247245},{"id":"DYp6.css","timestamp":1691431324811},{"id":"3VVr.css","timestamp":1691431360150},{"id":"rG2k.css","timestamp":1691431708777},{"id":"sDmc.css","timestamp":1691431738515},{"id":"50Hg.css","timestamp":1691431883053},{"id":"4X2N.css","timestamp":1691431979567},{"id":"YawJ.css","timestamp":1691432447534},{"id":"qskK.css","timestamp":1691432505460},{"id":"KcYz.css","timestamp":1691432521472},{"id":"KliC.css","timestamp":1691432539867},{"id":"KTuL.css","timestamp":1691432803637}]}