{"version":1,"resource":"vscode-remote://wsl%2Bubuntu/home/mattmcgovern/code/mmcgovern25/Connect-and-Clean/app/views/jobs/index.html.erb","entries":[{"id":"zzuh.erb","timestamp":1694464164343},{"id":"ySeW.erb","timestamp":1694464209543},{"id":"GVj9.erb","timestamp":1694464270793},{"id":"j92F.erb","timestamp":1694464311863},{"id":"eYM8.erb","timestamp":1694464415203},{"id":"tk4h.erb","timestamp":1694465007813},{"id":"QVtt.erb","timestamp":1694465027593},{"id":"gJus.erb","timestamp":1694465040793},{"id":"hUXJ.erb","timestamp":1694465056663},{"id":"mgXn.erb","timestamp":1694465069663},{"id":"jUzE.erb","timestamp":1694465398753},{"id":"qtvx.erb","timestamp":1694465432933},{"id":"0YDf.erb","timestamp":1694465449183},{"id":"Kw2u.erb","timestamp":1694465554893},{"id":"Qk2t.erb","timestamp":1694465594513},{"id":"jyAA.erb","source":"undoRedo.source","timestamp":1694623006309},{"id":"fzoU.erb","timestamp":1694699693607},{"id":"fCGj.erb","timestamp":1694699725587},{"id":"qsd6.erb","timestamp":1694699740067},{"id":"HEAc.erb","timestamp":1694699883617},{"id":"zMOL.erb","timestamp":1694699947077},{"id":"gV3p.erb","timestamp":1694700039587},{"id":"B8aY.erb","timestamp":1694700132437},{"id":"H05J.erb","source":"undoRedo.source","timestamp":1694700271557},{"id":"1Ma9.erb","timestamp":1694700368137},{"id":"WXMB.erb","timestamp":1694700428687},{"id":"J64e.erb","timestamp":1694701442216},{"id":"I3bF.erb","timestamp":1694701502656},{"id":"Z4lK.erb","timestamp":1694701539356},{"id":"6k3c.erb","timestamp":1694701601506},{"id":"Ozuy.erb","timestamp":1694701670956},{"id":"zVvF.erb","timestamp":1694701697786},{"id":"D6fg.erb","timestamp":1694701762726},{"id":"Kh0j.erb","timestamp":1694701787256},{"id":"Z046.erb","timestamp":1694701849196},{"id":"TAkn.erb","source":"undoRedo.source","timestamp":1694701871206},{"id":"u7gU.erb","timestamp":1694701881716},{"id":"vVOl.erb","timestamp":1694701893126},{"id":"0i0y.erb","timestamp":1694701974036},{"id":"i1Ez.erb","timestamp":1694701998356},{"id":"2B80.erb","timestamp":1694702087236},{"id":"fVa0.erb","timestamp":1694702133696},{"id":"Y3Y6.erb","timestamp":1694702147686},{"id":"VNRI.erb","timestamp":1694702256536},{"id":"E0N6.erb","timestamp":1694702847926},{"id":"i8Uo.erb","timestamp":1694703088096},{"id":"kYEE.erb","timestamp":1694703380366},{"id":"3KOH.erb","timestamp":1694703520946},{"id":"hxZq.erb","timestamp":1694703952456},{"id":"0RWt.erb","timestamp":1694705357736}]}