{"version":1,"resource":"vscode-remote://wsl%2Bubuntu/home/mattmcgovern/code/mmcgovern25/fullstack-challenges/04-Front-End/05-Events-and-Iterators/02-My-First-Event-Listener/lib/listener.js","entries":[{"id":"7co9.js","timestamp":1691776383897},{"id":"dgug.js","timestamp":1691776725439},{"id":"ud9R.js","timestamp":1691778164290},{"id":"sCuN.js","source":"undoRedo.source","timestamp":1691778230319},{"id":"dEP6.js","timestamp":1691778389277},{"id":"1bj7.js","timestamp":1691778415732},{"id":"yDMA.js","timestamp":1691778479865},{"id":"MHns.js","timestamp":1691778503211},{"id":"tz16.js","timestamp":1691960682501},{"id":"hUus.js","timestamp":1691960856271},{"id":"5qyw.js","timestamp":1691960991201}]}